odoo10_addon_l10n_es_aeat_sii_invoice_summary-10.0.1.0.0.99.dev4-py3.8-nspkg.pth
odoo/addons/l10n_es_aeat_sii_invoice_summary/README.rst
odoo/addons/l10n_es_aeat_sii_invoice_summary/__init__.py
odoo/addons/l10n_es_aeat_sii_invoice_summary/__manifest__.py
odoo/addons/l10n_es_aeat_sii_invoice_summary/i18n/es.po
odoo/addons/l10n_es_aeat_sii_invoice_summary/i18n/l10n_es_aeat_sii_invoice_summary.pot
odoo/addons/l10n_es_aeat_sii_invoice_summary/models/__init__.py
odoo/addons/l10n_es_aeat_sii_invoice_summary/models/account_invoice.py
odoo/addons/l10n_es_aeat_sii_invoice_summary/readme/CONTRIBUTORS.rst
odoo/addons/l10n_es_aeat_sii_invoice_summary/readme/DESCRIPTION.rst
odoo/addons/l10n_es_aeat_sii_invoice_summary/readme/ROADMAP.rst
odoo/addons/l10n_es_aeat_sii_invoice_summary/readme/USAGE.rst
odoo/addons/l10n_es_aeat_sii_invoice_summary/static/description/icon.png
odoo/addons/l10n_es_aeat_sii_invoice_summary/static/description/index.html
odoo/addons/l10n_es_aeat_sii_invoice_summary/views/account_invoice_view.xml
odoo10_addon_l10n_es_aeat_sii_invoice_summary-10.0.1.0.0.99.dev4.dist-info/METADATA
odoo10_addon_l10n_es_aeat_sii_invoice_summary-10.0.1.0.0.99.dev4.dist-info/WHEEL
odoo10_addon_l10n_es_aeat_sii_invoice_summary-10.0.1.0.0.99.dev4.dist-info/namespace_packages.txt
odoo10_addon_l10n_es_aeat_sii_invoice_summary-10.0.1.0.0.99.dev4.dist-info/top_level.txt
odoo10_addon_l10n_es_aeat_sii_invoice_summary-10.0.1.0.0.99.dev4.dist-info/RECORD
